{
    "key": "group_59cd17c716d21",
    "title": "Primary",
    "fields": [
        {
            "key": "field_59c40a57dca6d",
            "label": "Primary Blocks",
            "name": "primary_fields",
            "type": "flexible_content",
            "instructions": "",
            "required": 0,
            "conditional_logic": 0,
            "wrapper": {
                "width": "",
                "class": "",
                "id": ""
            },
            "layouts": {
                "598b6523d9343": {
                    "key": "598b6523d9343",
                    "name": "hero",
                    "label": "Hero",
                    "display": "block",
                    "sub_fields": [
                        {
                            "key": "field_59c40a57df900",
                            "label": "Image",
                            "name": "image",
                            "type": "image",
                            "instructions": "",
                            "required": 0,
                            "conditional_logic": 0,
                            "wrapper": {
                                "width": "50",
                                "class": "",
                                "id": ""
                            },
                            "return_format": "id",
                            "preview_size": "widescreen-desktop",
                            "library": "all",
                            "min_width": "",
                            "min_height": "",
                            "min_size": "",
                            "max_width": "",
                            "max_height": "",
                            "max_size": "",
                            "mime_types": ""
                        },
                        {
                            "key": "field_59c40a57df982",
                            "label": "Heading",
                            "name": "heading",
                            "type": "text",
                            "instructions": "",
                            "required": 0,
                            "conditional_logic": 0,
                            "wrapper": {
                                "width": "50",
                                "class": "",
                                "id": ""
                            },
                            "default_value": "",
                            "placeholder": "",
                            "prepend": "",
                            "append": "",
                            "maxlength": ""
                        },
                        {
                            "key": "field_59c40a57dfa00",
                            "label": "Copy",
                            "name": "copy",
                            "type": "textarea",
                            "instructions": "",
                            "required": 0,
                            "conditional_logic": 0,
                            "wrapper": {
                                "width": "100",
                                "class": "",
                                "id": ""
                            },
                            "default_value": "",
                            "placeholder": "",
                            "maxlength": "",
                            "rows": 3,
                            "new_lines": ""
                        },
                        {
                            "key": "field_59cd099dcdfaf",
                            "label": "Button",
                            "name": "button",
                            "type": "link",
                            "instructions": "",
                            "required": 0,
                            "conditional_logic": 0,
                            "wrapper": {
                                "width": "33",
                                "class": "",
                                "id": ""
                            },
                            "return_format": "array"
                        }
                    ],
                    "min": "",
                    "max": ""
                },
                "layout_5cd07c2a1538a": {
                    "key": "layout_5cd07c2a1538a",
                    "name": "hero_random",
                    "label": "Hero Random",
                    "display": "block",
                    "sub_fields": [
                        {
                            "key": "field_5cd07c4e1538c",
                            "label": "Heading",
                            "name": "heading",
                            "type": "text",
                            "instructions": "",
                            "required": 0,
                            "conditional_logic": 0,
                            "wrapper": {
                                "width": "",
                                "class": "",
                                "id": ""
                            },
                            "default_value": "",
                            "placeholder": "",
                            "prepend": "",
                            "append": "",
                            "maxlength": ""
                        },
                        {
                            "key": "field_5cd07c5d1538d",
                            "label": "Copy",
                            "name": "copy",
                            "type": "textarea",
                            "instructions": "",
                            "required": 0,
                            "conditional_logic": 0,
                            "wrapper": {
                                "width": "",
                                "class": "",
                                "id": ""
                            },
                            "default_value": "",
                            "placeholder": "",
                            "maxlength": "",
                            "rows": "",
                            "new_lines": ""
                        },
                        {
                            "key": "field_5cd07c671538e",
                            "label": "Button",
                            "name": "button",
                            "type": "link",
                            "instructions": "",
                            "required": 0,
                            "conditional_logic": 0,
                            "wrapper": {
                                "width": "",
                                "class": "",
                                "id": ""
                            },
                            "return_format": "array"
                        },
                        {
                            "key": "field_5cd07c331538b",
                            "label": "Gallery",
                            "name": "gallery",
                            "type": "gallery",
                            "instructions": "",
                            "required": 0,
                            "conditional_logic": 0,
                            "wrapper": {
                                "width": "",
                                "class": "",
                                "id": ""
                            },
                            "min": "",
                            "max": "",
                            "insert": "append",
                            "library": "all",
                            "min_width": "",
                            "min_height": "",
                            "min_size": "",
                            "max_width": "",
                            "max_height": "",
                            "max_size": "",
                            "mime_types": ""
                        }
                    ],
                    "min": "",
                    "max": ""
                },
                "layout_5cc844f387e7a": {
                    "key": "layout_5cc844f387e7a",
                    "name": "basic",
                    "label": "Basic Content",
                    "display": "block",
                    "sub_fields": [
                        {
                            "key": "field_5cc844fe87e7b",
                            "label": "Heading",
                            "name": "heading",
                            "type": "text",
                            "instructions": "",
                            "required": 0,
                            "conditional_logic": 0,
                            "wrapper": {
                                "width": "",
                                "class": "",
                                "id": ""
                            },
                            "default_value": "",
                            "placeholder": "",
                            "prepend": "",
                            "append": "",
                            "maxlength": ""
                        },
                        {
                            "key": "field_5cc8450987e7c",
                            "label": "Content",
                            "name": "content",
                            "type": "wysiwyg",
                            "instructions": "",
                            "required": 0,
                            "conditional_logic": 0,
                            "wrapper": {
                                "width": "",
                                "class": "",
                                "id": ""
                            },
                            "default_value": "",
                            "tabs": "all",
                            "toolbar": "full",
                            "media_upload": 1,
                            "delay": 0
                        }
                    ],
                    "min": "",
                    "max": ""
                },
                "598b6d31f945f": {
                    "key": "598b6d31f945f",
                    "name": "blocks",
                    "label": "CTA Blocks",
                    "display": "block",
                    "sub_fields": [
                        {
                            "key": "field_5a27019f665cb",
                            "label": "Heading",
                            "name": "heading",
                            "type": "text",
                            "instructions": "",
                            "required": 0,
                            "conditional_logic": [
                                [
                                    {
                                        "field": "field_5a27017d665ca",
                                        "operator": "==",
                                        "value": "1"
                                    }
                                ]
                            ],
                            "wrapper": {
                                "width": "",
                                "class": "",
                                "id": ""
                            },
                            "default_value": "",
                            "placeholder": "",
                            "prepend": "",
                            "append": "",
                            "maxlength": ""
                        },
                        {
                            "key": "field_59c40a57e006c",
                            "label": "CTAs",
                            "name": "cta_repeater",
                            "type": "repeater",
                            "instructions": "",
                            "required": 0,
                            "conditional_logic": 0,
                            "wrapper": {
                                "width": "",
                                "class": "",
                                "id": ""
                            },
                            "collapsed": "",
                            "min": 0,
                            "max": 0,
                            "layout": "block",
                            "button_label": "Add CTA",
                            "sub_fields": [
                                {
                                    "key": "field_5a204a31528e0",
                                    "label": "Title",
                                    "name": "title",
                                    "type": "text",
                                    "instructions": "",
                                    "required": 0,
                                    "conditional_logic": [
                                        [
                                            {
                                                "field": "field_59c40a57dca6d",
                                                "operator": "!=empty"
                                            }
                                        ]
                                    ],
                                    "wrapper": {
                                        "width": "25",
                                        "class": "",
                                        "id": ""
                                    },
                                    "default_value": "",
                                    "placeholder": "",
                                    "prepend": "",
                                    "append": "",
                                    "maxlength": ""
                                },
                                {
                                    "key": "field_5cc764dea419c",
                                    "label": "Copy",
                                    "name": "copy",
                                    "type": "textarea",
                                    "instructions": "",
                                    "required": 0,
                                    "conditional_logic": 0,
                                    "wrapper": {
                                        "width": "25",
                                        "class": "",
                                        "id": ""
                                    },
                                    "default_value": "",
                                    "placeholder": "",
                                    "maxlength": "",
                                    "rows": "",
                                    "new_lines": ""
                                },
                                {
                                    "key": "field_5cc764eca419d",
                                    "label": "Learn More",
                                    "name": "learn_more",
                                    "type": "link",
                                    "instructions": "",
                                    "required": 0,
                                    "conditional_logic": 0,
                                    "wrapper": {
                                        "width": "25",
                                        "class": "",
                                        "id": ""
                                    },
                                    "return_format": "array"
                                },
                                {
                                    "key": "field_5cc76502a419e",
                                    "label": "Download Requirements",
                                    "name": "download_requirements",
                                    "type": "link",
                                    "instructions": "",
                                    "required": 0,
                                    "conditional_logic": 0,
                                    "wrapper": {
                                        "width": "25",
                                        "class": "",
                                        "id": ""
                                    },
                                    "return_format": "array"
                                }
                            ]
                        }
                    ],
                    "min": "",
                    "max": ""
                },
                "layout_5c7de36e49d8e": {
                    "key": "layout_5c7de36e49d8e",
                    "name": "cta_drop",
                    "label": "CTA Drop",
                    "display": "block",
                    "sub_fields": [
                        {
                            "key": "field_5c7df4226fe70",
                            "label": "CTA Item",
                            "name": "cta_item",
                            "type": "repeater",
                            "instructions": "",
                            "required": 0,
                            "conditional_logic": 0,
                            "wrapper": {
                                "width": "",
                                "class": "",
                                "id": ""
                            },
                            "collapsed": "",
                            "min": 0,
                            "max": 0,
                            "layout": "row",
                            "button_label": "Add CTA",
                            "sub_fields": [
                                {
                                    "key": "field_5c7de3b449d90",
                                    "label": "Service Name",
                                    "name": "name",
                                    "type": "text",
                                    "instructions": "",
                                    "required": 0,
                                    "conditional_logic": 0,
                                    "wrapper": {
                                        "width": "",
                                        "class": "",
                                        "id": ""
                                    },
                                    "default_value": "",
                                    "placeholder": "",
                                    "prepend": "",
                                    "append": "",
                                    "maxlength": ""
                                },
                                {
                                    "key": "field_5cc6febcd663c",
                                    "label": "Service Copy",
                                    "name": "copy",
                                    "type": "textarea",
                                    "instructions": "",
                                    "required": 0,
                                    "conditional_logic": 0,
                                    "wrapper": {
                                        "width": "",
                                        "class": "",
                                        "id": ""
                                    },
                                    "default_value": "",
                                    "placeholder": "",
                                    "maxlength": "",
                                    "rows": 2,
                                    "new_lines": ""
                                },
                                {
                                    "key": "field_5c7de3c249d91",
                                    "label": "Heading",
                                    "name": "heading",
                                    "type": "textarea",
                                    "instructions": "",
                                    "required": 0,
                                    "conditional_logic": 0,
                                    "wrapper": {
                                        "width": "",
                                        "class": "",
                                        "id": ""
                                    },
                                    "default_value": "",
                                    "placeholder": "",
                                    "maxlength": "",
                                    "rows": 2,
                                    "new_lines": ""
                                },
                                {
                                    "key": "field_5cc9c31766870",
                                    "label": "Pitch",
                                    "name": "pitch",
                                    "type": "textarea",
                                    "instructions": "",
                                    "required": 0,
                                    "conditional_logic": 0,
                                    "wrapper": {
                                        "width": "",
                                        "class": "",
                                        "id": ""
                                    },
                                    "default_value": "",
                                    "placeholder": "",
                                    "maxlength": "",
                                    "rows": 4,
                                    "new_lines": ""
                                },
                                {
                                    "key": "field_5c7de3d949d92",
                                    "label": "Button",
                                    "name": "button",
                                    "type": "link",
                                    "instructions": "",
                                    "required": 0,
                                    "conditional_logic": 0,
                                    "wrapper": {
                                        "width": "",
                                        "class": "",
                                        "id": ""
                                    },
                                    "return_format": "array"
                                },
                                {
                                    "key": "field_5cfff40b3eccb",
                                    "label": "Button 2",
                                    "name": "button_2",
                                    "type": "link",
                                    "instructions": "",
                                    "required": 0,
                                    "conditional_logic": 0,
                                    "wrapper": {
                                        "width": "",
                                        "class": "",
                                        "id": ""
                                    },
                                    "return_format": "array"
                                },
                                {
                                    "key": "field_5cfff5ff09d46",
                                    "label": "Button 3",
                                    "name": "button_3",
                                    "type": "link",
                                    "instructions": "",
                                    "required": 0,
                                    "conditional_logic": 0,
                                    "wrapper": {
                                        "width": "",
                                        "class": "",
                                        "id": ""
                                    },
                                    "return_format": "array"
                                },
                                {
                                    "key": "field_5c7de3f249d93",
                                    "label": "Case",
                                    "name": "case",
                                    "type": "post_object",
                                    "instructions": "",
                                    "required": 0,
                                    "conditional_logic": 0,
                                    "wrapper": {
                                        "width": "",
                                        "class": "",
                                        "id": ""
                                    },
                                    "post_type": [
                                        "stories"
                                    ],
                                    "taxonomy": "",
                                    "allow_null": 0,
                                    "multiple": 0,
                                    "return_format": "object",
                                    "ui": 1
                                }
                            ]
                        }
                    ],
                    "min": "",
                    "max": ""
                },
                "59bc16088b070": {
                    "key": "59bc16088b070",
                    "name": "single_cta",
                    "label": "Single CTA",
                    "display": "block",
                    "sub_fields": [
                        {
                            "key": "field_5cc7028befa27",
                            "label": "Image",
                            "name": "image",
                            "type": "image",
                            "instructions": "",
                            "required": 0,
                            "conditional_logic": 0,
                            "wrapper": {
                                "width": "",
                                "class": "",
                                "id": ""
                            },
                            "return_format": "id",
                            "preview_size": "thumbnail",
                            "library": "all",
                            "min_width": "",
                            "min_height": "",
                            "min_size": "",
                            "max_width": "",
                            "max_height": "",
                            "max_size": "",
                            "mime_types": ""
                        },
                        {
                            "key": "field_5a2700eab6c84",
                            "label": "Heading",
                            "name": "heading",
                            "type": "textarea",
                            "instructions": "",
                            "required": 0,
                            "conditional_logic": 0,
                            "wrapper": {
                                "width": "",
                                "class": "",
                                "id": ""
                            },
                            "default_value": "",
                            "placeholder": "",
                            "maxlength": "",
                            "rows": "",
                            "new_lines": "br"
                        },
                        {
                            "key": "field_5a27000fae6b0",
                            "label": "Copy",
                            "name": "copy",
                            "type": "textarea",
                            "instructions": "",
                            "required": 0,
                            "conditional_logic": 0,
                            "wrapper": {
                                "width": "",
                                "class": "",
                                "id": ""
                            },
                            "default_value": "",
                            "placeholder": "",
                            "maxlength": "",
                            "rows": 3,
                            "new_lines": "br"
                        },
                        {
                            "key": "field_5cc702a5efa28",
                            "label": "Text Link",
                            "name": "text_link",
                            "type": "link",
                            "instructions": "",
                            "required": 0,
                            "conditional_logic": 0,
                            "wrapper": {
                                "width": "",
                                "class": "",
                                "id": ""
                            },
                            "return_format": "array"
                        }
                    ],
                    "min": "",
                    "max": ""
                },
                "layout_5c7eaad433772": {
                    "key": "layout_5c7eaad433772",
                    "name": "cta_buttons",
                    "label": "CTA Buttons",
                    "display": "block",
                    "sub_fields": [
                        {
                            "key": "field_5c7eaad533775",
                            "label": "Heading",
                            "name": "heading",
                            "type": "textarea",
                            "instructions": "",
                            "required": 0,
                            "conditional_logic": [
                                [
                                    {
                                        "field": "field_59c40a57dca6d",
                                        "operator": "!=empty"
                                    }
                                ]
                            ],
                            "wrapper": {
                                "width": "",
                                "class": "",
                                "id": ""
                            },
                            "default_value": "",
                            "placeholder": "",
                            "maxlength": "",
                            "rows": 2,
                            "new_lines": "br"
                        },
                        {
                            "key": "field_5c7eaad533776",
                            "label": "Buttons",
                            "name": "buttons",
                            "type": "repeater",
                            "instructions": "",
                            "required": 0,
                            "conditional_logic": 0,
                            "wrapper": {
                                "width": "",
                                "class": "",
                                "id": ""
                            },
                            "collapsed": "",
                            "min": 0,
                            "max": 0,
                            "layout": "block",
                            "button_label": "Add Button",
                            "sub_fields": [
                                {
                                    "key": "field_5c7eaad53377c",
                                    "label": "Button",
                                    "name": "button",
                                    "type": "link",
                                    "instructions": "",
                                    "required": 0,
                                    "conditional_logic": 0,
                                    "wrapper": {
                                        "width": "",
                                        "class": "",
                                        "id": ""
                                    },
                                    "return_format": "array"
                                }
                            ]
                        }
                    ],
                    "min": "",
                    "max": ""
                },
                "5a284337d4381": {
                    "key": "5a284337d4381",
                    "name": "success",
                    "label": "Success Story",
                    "display": "block",
                    "sub_fields": [
                        {
                            "key": "field_5cc70ad887a2c",
                            "label": "Selection",
                            "name": "selection",
                            "type": "post_object",
                            "instructions": "",
                            "required": 0,
                            "conditional_logic": 0,
                            "wrapper": {
                                "width": "",
                                "class": "",
                                "id": ""
                            },
                            "post_type": [
                                "stories"
                            ],
                            "taxonomy": "",
                            "allow_null": 0,
                            "multiple": 0,
                            "return_format": "object",
                            "ui": 1
                        }
                    ],
                    "min": "",
                    "max": ""
                },
                "layout_5c7ea639c91a5": {
                    "key": "layout_5c7ea639c91a5",
                    "name": "team_feed",
                    "label": "Team Feed",
                    "display": "block",
                    "sub_fields": [
                        {
                            "key": "field_5c7ea639c91a7",
                            "label": "Heading",
                            "name": "heading",
                            "type": "text",
                            "instructions": "",
                            "required": 0,
                            "conditional_logic": 0,
                            "wrapper": {
                                "width": "50",
                                "class": "",
                                "id": ""
                            },
                            "default_value": "",
                            "placeholder": "",
                            "prepend": "",
                            "append": "",
                            "maxlength": ""
                        }
                    ],
                    "min": "",
                    "max": ""
                },
                "layout_5c7df58f9fdc3": {
                    "key": "layout_5c7df58f9fdc3",
                    "name": "video",
                    "label": "Video",
                    "display": "block",
                    "sub_fields": [
                        {
                            "key": "field_5c7df5989fdc4",
                            "label": "Title",
                            "name": "title",
                            "type": "text",
                            "instructions": "",
                            "required": 0,
                            "conditional_logic": 0,
                            "wrapper": {
                                "width": "50",
                                "class": "",
                                "id": ""
                            },
                            "default_value": "",
                            "placeholder": "",
                            "prepend": "",
                            "append": "",
                            "maxlength": ""
                        },
                        {
                            "key": "field_5c7df5ab9fdc5",
                            "label": "Description",
                            "name": "description",
                            "type": "textarea",
                            "instructions": "",
                            "required": 0,
                            "conditional_logic": 0,
                            "wrapper": {
                                "width": "50",
                                "class": "",
                                "id": ""
                            },
                            "default_value": "",
                            "placeholder": "",
                            "maxlength": "",
                            "rows": "",
                            "new_lines": ""
                        },
                        {
                            "key": "field_5c7df5b29fdc6",
                            "label": "Video",
                            "name": "video",
                            "type": "oembed",
                            "instructions": "",
                            "required": 0,
                            "conditional_logic": 0,
                            "wrapper": {
                                "width": "",
                                "class": "",
                                "id": ""
                            },
                            "width": 1280,
                            "height": 600
                        }
                    ],
                    "min": "",
                    "max": ""
                },
                "layout_5cc848b5ed124": {
                    "key": "layout_5cc848b5ed124",
                    "name": "lending",
                    "label": "Lending Blocks",
                    "display": "block",
                    "sub_fields": [
                        {
                            "key": "field_5cc848cced125",
                            "label": "Tiers",
                            "name": "tiers",
                            "type": "repeater",
                            "instructions": "",
                            "required": 0,
                            "conditional_logic": 0,
                            "wrapper": {
                                "width": "",
                                "class": "",
                                "id": ""
                            },
                            "collapsed": "",
                            "min": 0,
                            "max": 0,
                            "layout": "row",
                            "button_label": "Add a Tier",
                            "sub_fields": [
                                {
                                    "key": "field_5cc84919ed126",
                                    "label": "Heading",
                                    "name": "heading",
                                    "type": "text",
                                    "instructions": "",
                                    "required": 0,
                                    "conditional_logic": 0,
                                    "wrapper": {
                                        "width": "",
                                        "class": "",
                                        "id": ""
                                    },
                                    "default_value": "",
                                    "placeholder": "",
                                    "prepend": "",
                                    "append": "",
                                    "maxlength": ""
                                },
                                {
                                    "key": "field_5cc8492ded127",
                                    "label": "Description",
                                    "name": "description",
                                    "type": "textarea",
                                    "instructions": "",
                                    "required": 0,
                                    "conditional_logic": 0,
                                    "wrapper": {
                                        "width": "",
                                        "class": "",
                                        "id": ""
                                    },
                                    "default_value": "",
                                    "placeholder": "",
                                    "maxlength": "",
                                    "rows": 2,
                                    "new_lines": ""
                                },
                                {
                                    "key": "field_5cc84970ed128",
                                    "label": "Information",
                                    "name": "information",
                                    "type": "wysiwyg",
                                    "instructions": "Heading 4s only.",
                                    "required": 0,
                                    "conditional_logic": 0,
                                    "wrapper": {
                                        "width": "",
                                        "class": "",
                                        "id": ""
                                    },
                                    "default_value": "",
                                    "tabs": "visual",
                                    "toolbar": "basic",
                                    "media_upload": 0,
                                    "delay": 0
                                },
                                {
                                    "key": "field_5cc9e491a172b",
                                    "label": "Requirements",
                                    "name": "requirements",
                                    "type": "url",
                                    "instructions": "",
                                    "required": 0,
                                    "conditional_logic": 0,
                                    "wrapper": {
                                        "width": "",
                                        "class": "",
                                        "id": ""
                                    },
                                    "default_value": "",
                                    "placeholder": ""
                                }
                            ]
                        }
                    ],
                    "min": "",
                    "max": ""
                },
                "layout_5cc8630e0c228": {
                    "key": "layout_5cc8630e0c228",
                    "name": "locations",
                    "label": "Locations Blocks",
                    "display": "block",
                    "sub_fields": [
                        {
                            "key": "field_5cc864fa98fa3",
                            "label": "Location",
                            "name": "location",
                            "type": "repeater",
                            "instructions": "",
                            "required": 0,
                            "conditional_logic": 0,
                            "wrapper": {
                                "width": "",
                                "class": "",
                                "id": ""
                            },
                            "collapsed": "",
                            "min": 0,
                            "max": 0,
                            "layout": "block",
                            "button_label": "",
                            "sub_fields": [
                                {
                                    "key": "field_5cc8631d0c229",
                                    "label": "Image",
                                    "name": "image",
                                    "type": "image",
                                    "instructions": "",
                                    "required": 0,
                                    "conditional_logic": 0,
                                    "wrapper": {
                                        "width": "33",
                                        "class": "",
                                        "id": ""
                                    },
                                    "return_format": "id",
                                    "preview_size": "thumbnail",
                                    "library": "all",
                                    "min_width": "",
                                    "min_height": "",
                                    "min_size": "",
                                    "max_width": "",
                                    "max_height": "",
                                    "max_size": "",
                                    "mime_types": ""
                                },
                                {
                                    "key": "field_5cc8633f0c22a",
                                    "label": "Name",
                                    "name": "name",
                                    "type": "text",
                                    "instructions": "",
                                    "required": 0,
                                    "conditional_logic": 0,
                                    "wrapper": {
                                        "width": "33",
                                        "class": "",
                                        "id": ""
                                    },
                                    "default_value": "",
                                    "placeholder": "",
                                    "prepend": "",
                                    "append": "",
                                    "maxlength": ""
                                },
                                {
                                    "key": "field_5cc863450c22b",
                                    "label": "Address",
                                    "name": "address",
                                    "type": "textarea",
                                    "instructions": "",
                                    "required": 0,
                                    "conditional_logic": 0,
                                    "wrapper": {
                                        "width": "33",
                                        "class": "",
                                        "id": ""
                                    },
                                    "default_value": "",
                                    "placeholder": "",
                                    "maxlength": "",
                                    "rows": 2,
                                    "new_lines": "br"
                                },
                                {
                                    "key": "field_5cc863580c22c",
                                    "label": "Phone",
                                    "name": "phone",
                                    "type": "text",
                                    "instructions": "",
                                    "required": 0,
                                    "conditional_logic": 0,
                                    "wrapper": {
                                        "width": "33",
                                        "class": "",
                                        "id": ""
                                    },
                                    "default_value": "",
                                    "placeholder": "",
                                    "prepend": "",
                                    "append": "",
                                    "maxlength": ""
                                },
                                {
                                    "key": "field_5cc863760c22d",
                                    "label": "Google Maps URL",
                                    "name": "maps",
                                    "type": "url",
                                    "instructions": "",
                                    "required": 0,
                                    "conditional_logic": 0,
                                    "wrapper": {
                                        "width": "33",
                                        "class": "",
                                        "id": ""
                                    },
                                    "default_value": "",
                                    "placeholder": ""
                                }
                            ]
                        }
                    ],
                    "min": "",
                    "max": ""
                },
                "layout_5cc8697be29d4": {
                    "key": "layout_5cc8697be29d4",
                    "name": "contact",
                    "label": "Contact",
                    "display": "block",
                    "sub_fields": [
                        {
                            "key": "field_5cc86983e29d5",
                            "label": "Automatically populated",
                            "name": "",
                            "type": "message",
                            "instructions": "",
                            "required": 0,
                            "conditional_logic": 0,
                            "wrapper": {
                                "width": "",
                                "class": "",
                                "id": ""
                            },
                            "message": "This form is automatically populated.",
                            "new_lines": "wpautop",
                            "esc_html": 0
                        }
                    ],
                    "min": "",
                    "max": ""
                }
            },
            "button_label": "Add Block",
            "min": "",
            "max": ""
        }
    ],
    "location": [
        [
            {
                "param": "page_template",
                "operator": "==",
                "value": "page-landing.php"
            }
        ],
        [
            {
                "param": "page_template",
                "operator": "==",
                "value": "page-sidebar.php"
            }
        ],
        [
            {
                "param": "page_template",
                "operator": "==",
                "value": "page-contact.php"
            }
        ]
    ],
    "menu_order": 0,
    "position": "normal",
    "style": "default",
    "label_placement": "top",
    "instruction_placement": "label",
    "hide_on_screen": [
        "the_content"
    ],
    "active": 1,
    "description": "",
    "modified": 1560278548
}